spymicmac/__init__.py
spymicmac/data.py
spymicmac/ee_tools.py
spymicmac/image.py
spymicmac/matching.py
spymicmac/micmac.py
spymicmac/orientation.py
spymicmac/register.py
spymicmac/resample.py
spymicmac/tools/balance_images.py
spymicmac/tools/block_orientation.py
spymicmac/tools/combine_auto_measures.py
spymicmac/tools/create_localchantier_xml.py
spymicmac/tools/download_cop30_vrt.py
spymicmac/tools/find_reseau_grid.py
spymicmac/tools/generate_micmac_measures.py
spymicmac/tools/join_hexagon.py
spymicmac/tools/mosaic_micmac_tiles.py
spymicmac/tools/move_bad_tapas.py
spymicmac/tools/post_process_micmac.py
spymicmac/tools/preprocess_kh9.py
spymicmac/tools/register_ortho.py
spymicmac/tools/remove_crosses.py
spymicmac/tools/remove_measures.py
spymicmac/tools/resample_hexagon.py
spymicmac/tools/write_micmac_xml.py
spymicmac-0.2.0.dist-info/LICENSE
spymicmac-0.2.0.dist-info/METADATA
spymicmac-0.2.0.dist-info/WHEEL
spymicmac-0.2.0.dist-info/entry_points.txt
spymicmac-0.2.0.dist-info/top_level.txt
spymicmac-0.2.0.dist-info/RECORD
