Metadata-Version: 2.1
Name: spymicmac
Version: 0.2.0
Summary: a python package for processing KH-9 and historical aerial imagery using MicMac
Author-email: Bob McNabb <robertmcnabb@gmail.com>
License: GPL-3.0-or-later
Project-URL: Homepage, https://github.com/iamdonovan/spymicmac
Project-URL: Bug Tracker, https://github.com/iamdonovan/spymicmac/issues
Classifier: Intended Audience :: Science/Research
Classifier: License :: OSI Approved :: GNU General Public License v3 (GPLv3)
Classifier: Natural Language :: English
Classifier: Programming Language :: Python :: 3
Classifier: Programming Language :: Python :: 3.10
Classifier: Programming Language :: Python :: 3.11
Classifier: Programming Language :: Unix Shell
Classifier: Topic :: Scientific/Engineering :: GIS
Classifier: Topic :: Scientific/Engineering :: Image Processing
Requires-Python: >=3.10
License-File: LICENSE
Requires-Dist: geopandas
Requires-Dist: matplotlib
Requires-Dist: usgs
Requires-Dist: gdal
Requires-Dist: opencv-python
Requires-Dist: lxml
Requires-Dist: scikit-image (>=0.19)
Requires-Dist: pillow (>9.1.0)
Requires-Dist: pybob (>=0.25.1)
Requires-Dist: pyasn1
Requires-Dist: sphinx
Requires-Dist: sphinx-argparse
Requires-Dist: sphinx-rtd-theme
Requires-Dist: earthengine-api
